MANIFEST.in
README.rst
setup.cfg
setup.py
docs/HISTORY.txt
docs/LICENSE.GPL
docs/LICENSE.txt
ftw/__init__.py
ftw.solr.egg-info/PKG-INFO
ftw.solr.egg-info/SOURCES.txt
ftw.solr.egg-info/dependency_links.txt
ftw.solr.egg-info/entry_points.txt
ftw.solr.egg-info/namespace_packages.txt
ftw.solr.egg-info/not-zip-safe
ftw.solr.egg-info/requires.txt
ftw.solr.egg-info/top_level.txt
ftw/solr/__init__.py
ftw/solr/commands.py
ftw/solr/config.py
ftw/solr/configure.zcml
ftw/solr/connection.py
ftw/solr/contentlisting.py
ftw/solr/converters.py
ftw/solr/document.py
ftw/solr/handlers.py
ftw/solr/helpers.py
ftw/solr/indexer.py
ftw/solr/interfaces.py
ftw/solr/meta.zcml
ftw/solr/patches.py
ftw/solr/query.py
ftw/solr/schema.py
ftw/solr/search.py
ftw/solr/setuphandlers.py
ftw/solr/testing.py
ftw/solr/zcml.py
ftw/solr/browser/__init__.py
ftw/solr/browser/configure.zcml
ftw/solr/browser/maintenance.py
ftw/solr/profiles/default/browserlayer.xml
ftw/solr/profiles/default/componentregistry.xml
ftw/solr/profiles/default/metadata.xml
ftw/solr/profiles/default/registry.xml
ftw/solr/profiles/uninstall/browserlayer.xml
ftw/solr/profiles/uninstall/componentregistry.xml
ftw/solr/tests/__init__.py
ftw/solr/tests/test_config.py
ftw/solr/tests/test_connection.py
ftw/solr/tests/test_contentlisting.py
ftw/solr/tests/test_converters.py
ftw/solr/tests/test_document.py
ftw/solr/tests/test_handlers.py
ftw/solr/tests/test_helpers.py
ftw/solr/tests/test_indexer.py
ftw/solr/tests/test_integration.py
ftw/solr/tests/test_maintenance.py
ftw/solr/tests/test_query.py
ftw/solr/tests/test_response.py
ftw/solr/tests/test_schema.py
ftw/solr/tests/test_search.py
ftw/solr/tests/test_setup.py
ftw/solr/tests/utils.py
ftw/solr/tests/data/bad_request.json
ftw/solr/tests/data/config.json
ftw/solr/tests/data/config_langid.json
ftw/solr/tests/data/config_solr9.json
ftw/solr/tests/data/doc.json
ftw/solr/tests/data/file.blob
ftw/solr/tests/data/highlighting.json
ftw/solr/tests/data/schema.json
ftw/solr/tests/data/schema_langid.json
ftw/solr/tests/data/search.json
ftw/solr/tests/data/search_with_facets.json
ftw/solr/upgrades/__init__.py
ftw/solr/upgrades/20190816143230_add_enable_setting/__init__.py
ftw/solr/upgrades/20190816143230_add_enable_setting/registry.xml
