Metadata-Version: 2.1
Name: ftw.solr
Version: 2.14.1
Summary: Solr integration for Plone
Home-page: https://pypi.python.org/pypi/ftw.solr
Author: Thomas Buchberger
Author-email: t.buchberger@4teamwork.ch
License: GPL version 2
Keywords: Plone Solr
Classifier: Environment :: Web Environment
Classifier: Framework :: Plone
Classifier: Framework :: Plone :: 4.3
Classifier: Framework :: Plone :: 5.0
Classifier: Framework :: Plone :: 5.1
Classifier: Framework :: Plone :: 5.2
Classifier: Programming Language :: Python
Classifier: Programming Language :: Python :: 2.7
Classifier: Programming Language :: Python :: 3.7
Classifier: Programming Language :: Python :: 3.8
Classifier: Operating System :: OS Independent
Classifier: License :: OSI Approved :: GNU General Public License v2 (GPLv2)
Requires-Dist: setuptools
Requires-Dist: plone.app.contentlisting
Requires-Dist: plone.app.layout
Requires-Dist: plone.namedfile[blobs]
Requires-Dist: ftw.upgrade
Requires-Dist: six>=1.12.0
Provides-Extra: test
Requires-Dist: plone.app.testing; extra == "test"
Requires-Dist: plone.app.dexterity; extra == "test"
Requires-Dist: plone.testing; extra == "test"
Requires-Dist: plone.api; extra == "test"
Requires-Dist: plone.app.contenttypes; extra == "test"
Requires-Dist: pytz; extra == "test"
Requires-Dist: mock; extra == "test"
Requires-Dist: ftw.testing; extra == "test"
Provides-Extra: tests
Requires-Dist: plone.app.testing; extra == "tests"
Requires-Dist: plone.app.dexterity; extra == "tests"
Requires-Dist: plone.testing; extra == "tests"
Requires-Dist: plone.api; extra == "tests"
Requires-Dist: plone.app.contenttypes; extra == "tests"
Requires-Dist: pytz; extra == "tests"
Requires-Dist: mock; extra == "tests"
Requires-Dist: ftw.testing; extra == "tests"
Provides-Extra: cindexing
Requires-Dist: collective.indexing; extra == "cindexing"
